Workbook
Name PrecioPro: Assumptions!$B$5
Name PrecioProPlus: Assumptions!$B$6
Name PrecioFamily: Assumptions!$B$7
Name MarginPro: Assumptions!$B$10
Name MarginProPlus: Assumptions!$B$11
Name MarginFamily: Assumptions!$B$12
Name CACPro: Assumptions!$B$16
Name CACProPlus: Assumptions!$B$17
Name CACFamily: Assumptions!$B$18
Name ChurnPro: Assumptions!$B$21
Name ChurnProPlus: Assumptions!$B$22
Name ChurnFamily: Assumptions!$B$23

Sheet Assumptions
A1: WUBI - ASSUMPTIONS
A3: PRICING (MXN/month) | B3: Value
A4: Plan Free | B4: 0
A5: Plan Pro | B5: 149
A6: Plan Pro+ | B6: 249
A7: Plan Family | B7: 399
A9: GROSS MARGIN (%)
A10: Margin Pro | B10: 0.84
A11: Margin Pro+ | B11: 0.86
A12: Margin Family | B12: 0.88
A14: CAC PER PLAN (MXN)
A15: CAC Free | B15: 0
A16: CAC Pro | B16: 300
A17: CAC Pro+ | B17: 350
A18: CAC Family | B18: 400
A20: MONTHLY CHURN (%)
A21: Churn Pro | B21: 0.04
A22: Churn Pro+ | B22: 0.03
A23: Churn Family | B23: 0.02
A25: MONTHLY FIXED COSTS (MXN)
A26: Month 1-6 | B26: 6000
A27: Month 7-12 | B27: 8000
A28: Month 13-24 | B28: 20000
A30: NEW USERS PER MONTH | B30: Pro | C30: Pro+ | D30: Family
A31: Month 1-6 | B31: 25 | C31: 5 | D31: 2
A32: Month 7-12 | B32: 50 | C32: 15 | D32: 5
A33: Month 13-24 | B33: 100 | C33: 30 | D33: 20

Sheet User Growth
A1: Month | B1: New Pro | C1: Active Pro | D1: New Pro+ | E1: Active Pro+ | F1: New Family | G1: Active Family | H1: Total Active
A2: 1 | B2: =IF(A2<=6, Assumptions!$B$31, IF(A2<=12, Assumptions!$B$32, Assumptions!$B$33)) | C2: =B2 | D2: =IF(A2<=6, Assumptions!$C$31, IF(A2<=12, Assumptions!$C$32, Assumptions!$C$33)) | E2: =D2 | F2: =IF(A2<=6, Assumptions!$D$31, IF(A2<=12, Assumptions!$D$32, Assumptions!$D$33)) | G2: =F2 | H2: =C2+E2+G2
A3: 2 | B3: =IF(A3<=6, Assumptions!$B$31, IF(A3<=12, Assumptions!$B$32, Assumptions!$B$33)) | C3: =C2*(1-ChurnPro)+B3 | D3: =IF(A3<=6, Assumptions!$C$31, IF(A3<=12, Assumptions!$C$32, Assumptions!$C$33)) | E3: =E2*(1-ChurnProPlus)+D3 | F3: =IF(A3<=6, Assumptions!$D$31, IF(A3<=12, Assumptions!$D$32, Assumptions!$D$33)) | G3: =G2*(1-ChurnFamily)+F3 | H3: =C3+E3+G3
A4: 3 | B4: =IF(A4<=6, Assumptions!$B$31, IF(A4<=12, Assumptions!$B$32, Assumptions!$B$33)) | C4: =C3*(1-ChurnPro)+B4 | D4: =IF(A4<=6, Assumptions!$C$31, IF(A4<=12, Assumptions!$C$32, Assumptions!$C$33)) | E4: =E3*(1-ChurnProPlus)+D4 | F4: =IF(A4<=6, Assumptions!$D$31, IF(A4<=12, Assumptions!$D$32, Assumptions!$D$33)) | G4: =G3*(1-ChurnFamily)+F4 | H4: =C4+E4+G4
A5: 4 | B5: =IF(A5<=6, Assumptions!$B$31, IF(A5<=12, Assumptions!$B$32, Assumptions!$B$33)) | C5: =C4*(1-ChurnPro)+B5 | D5: =IF(A5<=6, Assumptions!$C$31, IF(A5<=12, Assumptions!$C$32, Assumptions!$C$33)) | E5: =E4*(1-ChurnProPlus)+D5 | F5: =IF(A5<=6, Assumptions!$D$31, IF(A5<=12, Assumptions!$D$32, Assumptions!$D$33)) | G5: =G4*(1-ChurnFamily)+F5 | H5: =C5+E5+G5
A6: 5 | B6: =IF(A6<=6, Assumptions!$B$31, IF(A6<=12, Assumptions!$B$32, Assumptions!$B$33)) | C6: =C5*(1-ChurnPro)+B6 | D6: =IF(A6<=6, Assumptions!$C$31, IF(A6<=12, Assumptions!$C$32, Assumptions!$C$33)) | E6: =E5*(1-ChurnProPlus)+D6 | F6: =IF(A6<=6, Assumptions!$D$31, IF(A6<=12, Assumptions!$D$32, Assumptions!$D$33)) | G6: =G5*(1-ChurnFamily)+F6 | H6: =C6+E6+G6
A7: 6 | B7: =IF(A7<=6, Assumptions!$B$31, IF(A7<=12, Assumptions!$B$32, Assumptions!$B$33)) | C7: =C6*(1-ChurnPro)+B7 | D7: =IF(A7<=6, Assumptions!$C$31, IF(A7<=12, Assumptions!$C$32, Assumptions!$C$33)) | E7: =E6*(1-ChurnProPlus)+D7 | F7: =IF(A7<=6, Assumptions!$D$31, IF(A7<=12, Assumptions!$D$32, Assumptions!$D$33)) | G7: =G6*(1-ChurnFamily)+F7 | H7: =C7+E7+G7
A8: 7 | B8: =IF(A8<=6, Assumptions!$B$31, IF(A8<=12, Assumptions!$B$32, Assumptions!$B$33)) | C8: =C7*(1-ChurnPro)+B8 | D8: =IF(A8<=6, Assumptions!$C$31, IF(A8<=12, Assumptions!$C$32, Assumptions!$C$33)) | E8: =E7*(1-ChurnProPlus)+D8 | F8: =IF(A8<=6, Assumptions!$D$31, IF(A8<=12, Assumptions!$D$32, Assumptions!$D$33)) | G8: =G7*(1-ChurnFamily)+F8 | H8: =C8+E8+G8
A9: 8 | B9: =IF(A9<=6, Assumptions!$B$31, IF(A9<=12, Assumptions!$B$32, Assumptions!$B$33)) | C9: =C8*(1-ChurnPro)+B9 | D9: =IF(A9<=6, Assumptions!$C$31, IF(A9<=12, Assumptions!$C$32, Assumptions!$C$33)) | E9: =E8*(1-ChurnProPlus)+D9 | F9: =IF(A9<=6, Assumptions!$D$31, IF(A9<=12, Assumptions!$D$32, Assumptions!$D$33)) | G9: =G8*(1-ChurnFamily)+F9 | H9: =C9+E9+G9
A10: 9 | B10: =IF(A10<=6, Assumptions!$B$31, IF(A10<=12, Assumptions!$B$32, Assumptions!$B$33)) | C10: =C9*(1-ChurnPro)+B10 | D10: =IF(A10<=6, Assumptions!$C$31, IF(A10<=12, Assumptions!$C$32, Assumptions!$C$33)) | E10: =E9*(1-ChurnProPlus)+D10 | F10: =IF(A10<=6, Assumptions!$D$31, IF(A10<=12, Assumptions!$D$32, Assumptions!$D$33)) | G10: =G9*(1-ChurnFamily)+F10 | H10: =C10+E10+G10
A11: 10 | B11: =IF(A11<=6, Assumptions!$B$31, IF(A11<=12, Assumptions!$B$32, Assumptions!$B$33)) | C11: =C10*(1-ChurnPro)+B11 | D11: =IF(A11<=6, Assumptions!$C$31, IF(A11<=12, Assumptions!$C$32, Assumptions!$C$33)) | E11: =E10*(1-ChurnProPlus)+D11 | F11: =IF(A11<=6, Assumptions!$D$31, IF(A11<=12, Assumptions!$D$32, Assumptions!$D$33)) | G11: =G10*(1-ChurnFamily)+F11 | H11: =C11+E11+G11
A12: 11 | B12: =IF(A12<=6, Assumptions!$B$31, IF(A12<=12, Assumptions!$B$32, Assumptions!$B$33)) | C12: =C11*(1-ChurnPro)+B12 | D12: =IF(A12<=6, Assumptions!$C$31, IF(A12<=12, Assumptions!$C$32, Assumptions!$C$33)) | E12: =E11*(1-ChurnProPlus)+D12 | F12: =IF(A12<=6, Assumptions!$D$31, IF(A12<=12, Assumptions!$D$32, Assumptions!$D$33)) | G12: =G11*(1-ChurnFamily)+F12 | H12: =C12+E12+G12
A13: 12 | B13: =IF(A13<=6, Assumptions!$B$31, IF(A13<=12, Assumptions!$B$32, Assumptions!$B$33)) | C13: =C12*(1-ChurnPro)+B13 | D13: =IF(A13<=6, Assumptions!$C$31, IF(A13<=12, Assumptions!$C$32, Assumptions!$C$33)) | E13: =E12*(1-ChurnProPlus)+D13 | F13: =IF(A13<=6, Assumptions!$D$31, IF(A13<=12, Assumptions!$D$32, Assumptions!$D$33)) | G13: =G12*(1-ChurnFamily)+F13 | H13: =C13+E13+G13
A14: 13 | B14: =IF(A14<=6, Assumptions!$B$31, IF(A14<=12, Assumptions!$B$32, Assumptions!$B$33)) | C14: =C13*(1-ChurnPro)+B14 | D14: =IF(A14<=6, Assumptions!$C$31, IF(A14<=12, Assumptions!$C$32, Assumptions!$C$33)) | E14: =E13*(1-ChurnProPlus)+D14 | F14: =IF(A14<=6, Assumptions!$D$31, IF(A14<=12, Assumptions!$D$32, Assumptions!$D$33)) | G14: =G13*(1-ChurnFamily)+F14 | H14: =C14+E14+G14
... A25: 24 | B25: =IF(A25<=6, Assumptions!$B$31, IF(A25<=12, Assumptions!$B$32, Assumptions!$B$33)) | C25: =C24*(1-ChurnPro)+B25 | D25: =IF(A25<=6, Assumptions!$C$31, IF(A25<=12, Assumptions!$C$32, Assumptions!$C$33)) | E25: =E24*(1-ChurnProPlus)+D25 | F25: =IF(A25<=6, Assumptions!$D$31, IF(A25<=12, Assumptions!$D$32, Assumptions!$D$33)) | G25: =G24*(1-ChurnFamily)+F25 | H25: =C25+E25+G25

Sheet P&L Projection
A1: Month | B1: MRR Pro | C1: MRR Pro+ | D1: MRR Family | E1: MRR Total | F1: Gross Margin | G1: Fixed Costs | H1: Net Profit | I1: Margin %
A2: 1 | B2: ='User Growth'!C2*PrecioPro | C2: ='User Growth'!E2*PrecioProPlus | D2: ='User Growth'!G2*PrecioFamily | E2: =B2+C2+D2 | F2: =B2*MarginPro+C2*MarginProPlus+D2*MarginFamily | G2: =IF(A2<=6,Assumptions!$B$26,IF(A2<=12,Assumptions!$B$27,Assumptions!$B$28)) | H2: =F2-G2 | I2: =IF(E2>0,H2/E2,0)
A3: 2 | B3: ='User Growth'!C3*PrecioPro | C3: ='User Growth'!E3*PrecioProPlus | D3: ='User Growth'!G3*PrecioFamily | E3: =B3+C3+D3 | F3: =B3*MarginPro+C3*MarginProPlus+D3*MarginFamily | G3: =IF(A3<=6,Assumptions!$B$26,IF(A3<=12,Assumptions!$B$27,Assumptions!$B$28)) | H3: =F3-G3 | I3: =IF(E3>0,H3/E3,0)
A4: 3 | B4: ='User Growth'!C4*PrecioPro | C4: ='User Growth'!E4*PrecioProPlus | D4: ='User Growth'!G4*PrecioFamily | E4: =B4+C4+D4 | F4: =B4*MarginPro+C4*MarginProPlus+D4*MarginFamily | G4: =IF(A4<=6,Assumptions!$B$26,IF(A4<=12,Assumptions!$B$27,Assumptions!$B$28)) | H4: =F4-G4 | I4: =IF(E4>0,H4/E4,0)
A5: 4 | B5: ='User Growth'!C5*PrecioPro | C5: ='User Growth'!E5*PrecioProPlus | D5: ='User Growth'!G5*PrecioFamily | E5: =B5+C5+D5 | F5: =B5*MarginPro+C5*MarginProPlus+D5*MarginFamily | G5: =IF(A5<=6,Assumptions!$B$26,IF(A5<=12,Assumptions!$B$27,Assumptions!$B$28)) | H5: =F5-G5 | I5: =IF(E5>0,H5/E5,0)
A6: 5 | B6: ='User Growth'!C6*PrecioPro | C6: ='User Growth'!E6*PrecioProPlus | D6: ='User Growth'!G6*PrecioFamily | E6: =B6+C6+D6 | F6: =B6*MarginPro+C6*MarginProPlus+D6*MarginFamily | G6: =IF(A6<=6,Assumptions!$B$26,IF(A6<=12,Assumptions!$B$27,Assumptions!$B$28)) | H6: =F6-G6 | I6: =IF(E6>0,H6/E6,0)
A7: 6 | B7: ='User Growth'!C7*PrecioPro | C7: ='User Growth'!E7*PrecioProPlus | D7: ='User Growth'!G7*PrecioFamily | E7: =B7+C7+D7 | F7: =B7*MarginPro+C7*MarginProPlus+D7*MarginFamily | G7: =IF(A7<=6,Assumptions!$B$26,IF(A7<=12,Assumptions!$B$27,Assumptions!$B$28)) | H7: =F7-G7 | I7: =IF(E7>0,H7/E7,0)
A8: 7 | B8: ='User Growth'!C8*PrecioPro | C8: ='User Growth'!E8*PrecioProPlus | D8: ='User Growth'!G8*PrecioFamily | E8: =B8+C8+D8 | F8: =B8*MarginPro+C8*MarginProPlus+D8*MarginFamily | G8: =IF(A8<=6,Assumptions!$B$26,IF(A8<=12,Assumptions!$B$27,Assumptions!$B$28)) | H8: =F8-G8 | I8: =IF(E8>0,H8/E8,0)
A9: 8 | B9: ='User Growth'!C9*PrecioPro | C9: ='User Growth'!E9*PrecioProPlus | D9: ='User Growth'!G9*PrecioFamily | E9: =B9+C9+D9 | F9: =B9*MarginPro+C9*MarginProPlus+D9*MarginFamily | G9: =IF(A9<=6,Assumptions!$B$26,IF(A9<=12,Assumptions!$B$27,Assumptions!$B$28)) | H9: =F9-G9 | I9: =IF(E9>0,H9/E9,0)
A10: 9 | B10: ='User Growth'!C10*PrecioPro | C10: ='User Growth'!E10*PrecioProPlus | D10: ='User Growth'!G10*PrecioFamily | E10: =B10+C10+D10 | F10: =B10*MarginPro+C10*MarginProPlus+D10*MarginFamily | G10: =IF(A10<=6,Assumptions!$B$26,IF(A10<=12,Assumptions!$B$27,Assumptions!$B$28)) | H10: =F10-G10 | I10: =IF(E10>0,H10/E10,0)
A11: 10 | B11: ='User Growth'!C11*PrecioPro | C11: ='User Growth'!E11*PrecioProPlus | D11: ='User Growth'!G11*PrecioFamily | E11: =B11+C11+D11 | F11: =B11*MarginPro+C11*MarginProPlus+D11*MarginFamily | G11: =IF(A11<=6,Assumptions!$B$26,IF(A11<=12,Assumptions!$B$27,Assumptions!$B$28)) | H11: =F11-G11 | I11: =IF(E11>0,H11/E11,0)
A12: 11 | B12: ='User Growth'!C12*PrecioPro | C12: ='User Growth'!E12*PrecioProPlus | D12: ='User Growth'!G12*PrecioFamily | E12: =B12+C12+D12 | F12: =B12*MarginPro+C12*MarginProPlus+D12*MarginFamily | G12: =IF(A12<=6,Assumptions!$B$26,IF(A12<=12,Assumptions!$B$27,Assumptions!$B$28)) | H12: =F12-G12 | I12: =IF(E12>0,H12/E12,0)
A13: 12 | B13: ='User Growth'!C13*PrecioPro | C13: ='User Growth'!E13*PrecioProPlus | D13: ='User Growth'!G13*PrecioFamily | E13: =B13+C13+D13 | F13: =B13*MarginPro+C13*MarginProPlus+D13*MarginFamily | G13: =IF(A13<=6,Assumptions!$B$26,IF(A13<=12,Assumptions!$B$27,Assumptions!$B$28)) | H13: =F13-G13 | I13: =IF(E13>0,H13/E13,0)
... A25: 24 | B25: ='User Growth'!C25*PrecioPro | C25: ='User Growth'!E25*PrecioProPlus | D25: ='User Growth'!G25*PrecioFamily | E25: =B25+C25+D25 | F25: =B25*MarginPro+C25*MarginProPlus+D25*MarginFamily | G25: =IF(A25<=6,Assumptions!$B$26,IF(A25<=12,Assumptions!$B$27,Assumptions!$B$28)) | H25: =F25-G25 | I25: =IF(E25>0,H25/E25,0)

Sheet Unit Economics
A1: UNIT ECONOMICS
B3: Pro | C3: Pro+ | D3: Family
A4: Price (MXN/month) | B4: =PrecioPro | C4: =PrecioProPlus | D4: =PrecioFamily
A5: Margin % | B5: =MarginPro | C5: =MarginProPlus | D5: =MarginFamily
A6: Monthly Churn % | B6: =ChurnPro | C6: =ChurnProPlus | D6: =ChurnFamily
A8: LTV (MXN) | B8: =B4*B5/B6 | C8: =C4*C5/C6 | D8: =D4*D5/D6
A9: CAC (MXN) | B9: =CACPro | C9: =CACProPlus | D9: =CACFamily
A10: LTV/CAC Ratio | B10: =IF(B9>0,B8/B9,0) | C10: =IF(C9>0,C8/C9,0) | D10: =IF(D9>0,D8/D9,0)
A12: Payback (months) | B12: =IF(B4*B5>0,B9/(B4*B5),0) | C12: =IF(C4*C5>0,C9/(C4*C5),0) | D12: =IF(D4*D5>0,D9/(D4*D5),0)
A13: Margin/User (MXN) | B13: =B4*B5 | C13: =C4*C5 | D13: =D4*D5

Sheet Dashboard
A1: WUBI - FINANCIAL DASHBOARD
B3: 6 Months | C3: 12 Months | D3: 24 Months
A5: USERS
A6: Total Users | B6: ='User Growth'!H7 | C6: ='User Growth'!H13 | D6: ='User Growth'!H25
A7: - Plan Pro | B7: ='User Growth'!C7 | C7: ='User Growth'!C13 | D7: ='User Growth'!C25
A8: - Plan Pro+ | B8: ='User Growth'!E7 | C8: ='User Growth'!E13 | D8: ='User Growth'!E25
A9: - Plan Family | B9: ='User Growth'!G7 | C9: ='User Growth'!G13 | D9: ='User Growth'!G25
A11: REVENUE
A12: MRR | B12: ='P&L Projection'!E7 | C12: ='P&L Projection'!E13 | D12: ='P&L Projection'!E25
A13: ARR | B13: =B12*12 | C13: =C12*12 | D13: =D12*12
A15: PROFITABILITY
A16: Gross Margin | B16: ='P&L Projection'!F7 | C16: ='P&L Projection'!F13 | D16: ='P&L Projection'!F25
A17: Fixed Costs | B17: ='P&L Projection'!G7 | C17: ='P&L Projection'!G13 | D17: ='P&L Projection'!G25
A18: Net Profit | B18: ='P&L Projection'!H7 | C18: ='P&L Projection'!H13 | D18: ='P&L Projection'!H25
A19: Margin % | B19: ='P&L Projection'!I7 | C19: ='P&L Projection'!I13 | D19: ='P&L Projection'!I25
A21: CUMULATIVE
A22: Cumul. Revenue | B22: =SUM('P&L Projection'!E2:E7) | C22: =SUM('P&L Projection'!E2:E13) | D22: =SUM('P&L Projection'!E2:E25)
A23: Cumul. Profit | B23: =SUM('P&L Projection'!H2:H7) | C23: =SUM('P&L Projection'!H2:H13) | D23: =SUM('P&L Projection'!H2:H25)
A25: UNIT ECONOMICS
A26: LTV/CAC Pro | B26: ='Unit Economics'!B10 | C26: ='Unit Economics'!B10 | D26: ='Unit Economics'!B10
A27: Payback Pro (months) | B27: ='Unit Economics'!B12 | C27: ='Unit Economics'!B12 | D27: ='Unit Economics'!B12

Sheet Scenarios
A1: SCENARIO ANALYSIS (24 MONTHS)
B3: Conservative | C3: Base | D3: Optimistic
A5: ASSUMPTIONS
A6: Churn Pro (%) | B6: 0.06 | C6: =ChurnPro | D6: 0.03
A7: CAC Pro (MXN) | B7: 400 | C7: =CACPro | D7: 200
A8: New Pro/month (M13-24) | B8: 50 | C8: =Assumptions!$B$33 | D8: 150
A9: Price Pro (MXN) | B9: =PrecioPro | C9: =PrecioPro | D9: =PrecioPro
A10: Margin Pro (%) | B10: =MarginPro | C10: =MarginPro | D10: =MarginPro
A12: ESTIMATED RESULTS
A13: Est. Active Pro Users | B13: =IF(B6>0, B8/B6, 0) | C13: =IF(C6>0, C8/C6, 0) | D13: =IF(D6>0, D8/D6, 0)
A14: Est. MRR Pro | B14: =B13*B9 | C14: =C13*C9 | D14: =D13*D9
A15: Est. Gross Margin | B15: =B14*B10 | C15: =C14*C10 | D15: =D14*D10
A16: LTV/CAC | B16: =IF(B7>0, (B9*B10/B6)/B7, 0) | C16: =IF(C7>0, (C9*C10/C6)/C7, 0) | D16: =IF(D7>0, (D9*D10/D6)/D7, 0)

Sheet Sensitivity
A1: SENSITIVITY ANALYSIS: LTV/CAC PLAN PRO
A3: CAC / Churn | B3: 3% | C3: 4% | D3: 5% | E3: 6% | F3: 7%
A4: 200 | B4: =(PrecioPro*MarginPro)/0.03/200 | C4: =(PrecioPro*MarginPro)/0.04/200 | D4: =(PrecioPro*MarginPro)/0.05/200 | E4: =(PrecioPro*MarginPro)/0.06/200 | F4: =(PrecioPro*MarginPro)/0.07/200
A5: 300 | B5: =(PrecioPro*MarginPro)/0.03/300 | C5: =(PrecioPro*MarginPro)/0.04/300 | D5: =(PrecioPro*MarginPro)/0.05/300 | E5: =(PrecioPro*MarginPro)/0.06/300 | F5: =(PrecioPro*MarginPro)/0.07/300
A6: 400 | B6: =(PrecioPro*MarginPro)/0.03/400 | C6: =(PrecioPro*MarginPro)/0.04/400 | D6: =(PrecioPro*MarginPro)/0.05/400 | E6: =(PrecioPro*MarginPro)/0.06/400 | F6: =(PrecioPro*MarginPro)/0.07/400
A7: 500 | B7: =(PrecioPro*MarginPro)/0.03/500 | C7: =(PrecioPro*MarginPro)/0.04/500 | D7: =(PrecioPro*MarginPro)/0.05/500 | E7: =(PrecioPro*MarginPro)/0.06/500 | F7: =(PrecioPro*MarginPro)/0.07/500
